promptlytics/__init__.py
promptlytics/promptlytics.py
promptlytics-0.0.2.dist-info/LICENSE
promptlytics-0.0.2.dist-info/METADATA
promptlytics-0.0.2.dist-info/WHEEL
promptlytics-0.0.2.dist-info/top_level.txt
promptlytics-0.0.2.dist-info/RECORD
