Metadata-Version: 2.1
Name: promptlytics
Version: 0.0.2
Summary: Python wrapper for Promptlytics
Home-page: https://www.promptlytics.co
Author: Promptlytics (Scott Cilento)
Author-email: scott@promptlytics.co
License: UNKNOWN
Platform: UNKNOWN
License-File: LICENSE
Requires-Dist: requests
